django_ts_bridge/__init__.py
django_ts_bridge/choices.py
django_ts_bridge/core.py
django_ts_bridge/fields.py
django_ts_bridge/mappings.py
django_ts_bridge/model_defs.py
django_ts_bridge/settings.py
django_ts_bridge/management/__init__.py
django_ts_bridge/management/commands/__init__.py
django_ts_bridge/management/commands/create_ts_choice_defs.py
django_ts_bridge/management/commands/create_ts_files.py
django_ts_bridge/management/commands/create_ts_serializer_types.py
django_ts_bridge/management/commands/create_ts_urls.py
django_ts_bridge/templates/django_ts_bridge/choices_ts.tpl
django_ts_bridge/templates/django_ts_bridge/urls_ts.tpl
django_ts_bridge/templatetags/__init__.py
django_ts_bridge/templatetags/django_ts_bridge.py
django_ts_bridge-1.3.3.dist-info/LICENSE
django_ts_bridge-1.3.3.dist-info/METADATA
django_ts_bridge-1.3.3.dist-info/WHEEL
django_ts_bridge-1.3.3.dist-info/top_level.txt
django_ts_bridge-1.3.3.dist-info/RECORD
