Metadata-Version: 2.1
Name: django-ts-bridge
Version: 1.3.3
Summary: Management commands in Django that give defintions for Django models returned by DRF along with any model fields limited by choices
Home-page: https://gitlab.com/ChickenF622/django-ts-bridge
Author: ChickenF622
Author-email: chickenf622@gmail.com
License: UNKNOWN
Platform: UNKNOWN
Classifier: Programming Language :: Python :: 3
Classifier: License :: OSI Approved :: GNU General Public License v3 (GPLv3)
Classifier: Operating System :: OS Independent
Requires-Python: >=3.8
License-File: LICENSE
Requires-Dist: asgiref (>=3.3.1)
Requires-Dist: Django (>=3.1.5)
Requires-Dist: djangorestframework (>=3.12.2)
Requires-Dist: pytz (>=2020.5)
Requires-Dist: sqlparse (>=0.4.1)
